tilores_langchain/__init__.py
tilores_langchain/tilores_tools.py
tilores_langchain-0.2.0.dist-info/LICENSE
tilores_langchain-0.2.0.dist-info/METADATA
tilores_langchain-0.2.0.dist-info/WHEEL
tilores_langchain-0.2.0.dist-info/top_level.txt
tilores_langchain-0.2.0.dist-info/RECORD
