Metadata-Version: 2.1
Name: tilores-langchain
Version: 0.2.0
Summary: This package contains tools to work with Tilores entity resolution database within Langchain.
Author-email: Lukas Rieder <lukas@parlant.co>, Stefan Berkner <stefan.berkner@tilores.io>
License: MIT License
Project-URL: Homepage, https://github.com/tilotech/tilores-langchain
Project-URL: Issues, https://github.com/tilotech/tilores-langchain/issues
Keywords: entity-resolution,tilores,graph-raq,identity-raq,langchain,langchain-tool
Classifier: Programming Language :: Python :: 3
Classifier: License :: OSI Approved :: MIT License
Classifier: Operating System :: OS Independent
Requires-Python: >=3.8
License-File: LICENSE
Requires-Dist: tilores-sdk>=0.4.0
Provides-Extra: all
Requires-Dist: tilores-langchain[langchain]; extra == "all"
Provides-Extra: langchain
Requires-Dist: langchain; extra == "langchain"
Requires-Dist: openai; extra == "langchain"
Provides-Extra: test
Requires-Dist: pytest==8.3.2; extra == "test"
